examples/__init__.py
examples/optimize_dvs.py
examples/pre_processing_pipeline/__init__.py
examples/pre_processing_pipeline/3_coregistration.py
examples/pre_processing_pipeline/0_parse_scanner_settings.py
examples/pre_processing_pipeline/4_create_binary_masks.py
examples/pre_processing_pipeline/1_write_phase_enc_dir.py
examples/pre_processing_pipeline/2_apply_corrections.py
mri_tools/__init__.py
mri_tools/shell_utils.py
mri_tools/common.py
mri_tools/wm_parcellation.py
mri_tools/pipelines/__init__.py
mri_tools/pipelines/tbss_wmp.py
mri_tools/tbss/__init__.py
mri_tools/tbss/tbss.py
mri_tools/tbss/nipype_overwrite/__init__.py
mri_tools/tbss/nipype_overwrite/tbss_workflow.py
mri_tools/dvs/__init__.py
mri_tools/dvs/io.py
mri_tools/dvs/plot.py
mri_tools/dvs/restructuring.py
mri_tools/dvs/base.py
mri_tools/scanner_settings/__init__.py
mri_tools/scanner_settings/parsers/__init__.py
mri_tools/scanner_settings/parsers/siemens.py
mri_tools/scanner_settings/parsers/common.py
mri_tools/topup_eddy/__init__.py
mri_tools/topup_eddy/common.py
mri_tools/topup_eddy/nipype_overwrite/__init__.py
mri_tools/topup_eddy/nipype_overwrite/all_peb_pipeline.py
mri_tools/plots/__init__.py
mri_tools/plots/widgets.py
mri_tools/plots/scatter_plots.py
mri_tools/plots/plot_tbss_wmp_results.py
mri_tools/plots/layouts.py
mri_tools/registration/__init__.py
mri_tools/registration/coregister.py
mri_tools/registration/common.py
mri_tools/registration/register_atlas.py
mri_tools-0.2.1.dist-info/metadata.json
mri_tools-0.2.1.dist-info/WHEEL
mri_tools-0.2.1.dist-info/DESCRIPTION.rst
mri_tools-0.2.1.dist-info/RECORD
mri_tools-0.2.1.dist-info/METADATA
mri_tools-0.2.1.dist-info/top_level.txt
tests/__init__.py
tests/test_mri_tools.py
