Metadata-Version: 2.0
Name: mri-tools
Version: 0.2.1
Summary: Various tools for MRI related work.
Home-page: https://github.com/robbert-harms/mri-tools
Author: Robbert Harms
Author-email: robbert.harms@maastrichtuniversity.nl
License: BSD 3-Clause
Keywords: mri-tools
Platform: UNKNOWN
Classifier: Environment :: Console
Classifier: Intended Audience :: Developers
Classifier: Intended Audience :: Science/Research
Classifier: License :: OSI Approved :: BSD License
Classifier: Natural Language :: English
Classifier: Operating System :: POSIX :: Linux
Classifier: Programming Language :: Python :: 2
Classifier: Programming Language :: Python :: 2.7
Classifier: Programming Language :: Python :: 3
Classifier: Programming Language :: Python :: 3.4
Classifier: Topic :: Scientific/Engineering
Requires-Dist: wheel (>=0.23.0)
Requires-Dist: numpy
Requires-Dist: scipy
Requires-Dist: nibabel
Requires-Dist: nipype
Requires-Dist: scikit-image
Requires-Dist: matplotlib
